ac_segmentation/__init__.py
ac_segmentation/deprecated/__init__.py
ac_segmentation/deprecated/add_radius.py
ac_segmentation/deprecated/postprocess.py
ac_segmentation/deprecated/preprocess.py
ac_segmentation/deprecated/reconnect_stack.py
ac_segmentation/deprecated/segmentation.py
ac_segmentation/deprecated/segmentation_stack.py
ac_segmentation/deprecated/segmentation_to_swc_stack.py
ac_segmentation/deprecated/swc_morphology/__init__.py
ac_segmentation/deprecated/swc_morphology/classes.py
ac_segmentation/deprecated/swc_morphology/readwrite_swc.py
ac_segmentation/neurotorch/__init__.py
ac_segmentation/neurotorch/augmentations/augmentation.py
ac_segmentation/neurotorch/augmentations/blur.py
ac_segmentation/neurotorch/augmentations/brightness.py
ac_segmentation/neurotorch/augmentations/dropped.py
ac_segmentation/neurotorch/augmentations/duplicate.py
ac_segmentation/neurotorch/augmentations/occlusion.py
ac_segmentation/neurotorch/augmentations/stitch.py
ac_segmentation/neurotorch/core/__init__.py
ac_segmentation/neurotorch/core/predictor.py
ac_segmentation/neurotorch/core/predictor_aff_ls.py
ac_segmentation/neurotorch/core/trainer.py
ac_segmentation/neurotorch/core/trainer_aff_ls.py
ac_segmentation/neurotorch/datasets/__init__.py
ac_segmentation/neurotorch/datasets/dataset.py
ac_segmentation/neurotorch/datasets/datatypes.py
ac_segmentation/neurotorch/datasets/filetypes.py
ac_segmentation/neurotorch/datasets/specification.py
ac_segmentation/neurotorch/loss/SimplePointWeighting.py
ac_segmentation/neurotorch/loss/affinity.py
ac_segmentation/neurotorch/nets/RSUNet.py
ac_segmentation/neurotorch/nets/RSUNetAff.py
ac_segmentation/neurotorch/nets/__init__.py
ac_segmentation/neurotorch/nets/layers.py
ac_segmentation/neurotorch/nets/netcollector.py
ac_segmentation/neurotorch/training/__init__.py
ac_segmentation/neurotorch/training/checkpoint.py
ac_segmentation/neurotorch/training/logging.py
ac_segmentation/neurotorch/utils/torch_utils.py
ac_segmentation-0.0.2.dist-info/LICENSE.txt
ac_segmentation-0.0.2.dist-info/METADATA
ac_segmentation-0.0.2.dist-info/WHEEL
ac_segmentation-0.0.2.dist-info/top_level.txt
ac_segmentation-0.0.2.dist-info/RECORD
