Metadata-Version: 2.1
Name: ac_segmentation
Version: 0.0.2
Summary: Segmentation for Axonal Connectomics
Author: Olga Gliko
License-File: LICENSE.txt
Requires-Dist: numpy>=1.16.0
Requires-Dist: scikit-build>=0.13
Requires-Dist: cloud-files
Requires-Dist: torch==2.2.0
Requires-Dist: tifffile==2023.1.23.1
Requires-Dist: h5py>=2.7.1
Requires-Dist: psutil>=5.4.7
Requires-Dist: natsort>=7.0.0
Requires-Dist: opencv-python-headless
Requires-Dist: scikit-image>=0.14.2
Requires-Dist: scikit-learn
Requires-Dist: pandas
Requires-Dist: joblib
Requires-Dist: kimimaro
Requires-Dist: zarr
Requires-Dist: argschema
Requires-Dist: tensorstore
Requires-Dist: shapely
Requires-Dist: scipy
Requires-Dist: connected-components-3d
Requires-Dist: navis
Requires-Dist: docker
Requires-Dist: cloud-volume==10.1.0
Requires-Dist: jsonschema==4.18.0
